signal_ICT_Kenil_parekh_92400133150/__init__.py
signal_ICT_Kenil_parekh_92400133150/operations.py
signal_ICT_Kenil_parekh_92400133150/trigonometric_signals.py
signal_ICT_Kenil_parekh_92400133150/unitary_signals.py
signal_ict_kenil_parekh_92400133150-1.0.0.dist-info/METADATA
signal_ict_kenil_parekh_92400133150-1.0.0.dist-info/WHEEL
signal_ict_kenil_parekh_92400133150-1.0.0.dist-info/top_level.txt
signal_ict_kenil_parekh_92400133150-1.0.0.dist-info/RECORD
