Metadata-Version: 2.4
Name: signal_ICT_Kenil_parekh_92400133150
Version: 1.0.0
Summary: Python package for signal processing exercises
Author: Kenil parekh
Requires-Python: >=3.6
Requires-Dist: numpy
Requires-Dist: matplotlib
Dynamic: author
Dynamic: requires-dist
Dynamic: requires-python
Dynamic: summary
